{"$schema": "https://vega.github.io/schema/vega/v5.json", "width": 600, "height": 400, "padding": 10, "data": [{"name": "table", "transform": [{"type": "filter", "expr": "datum.practica==Practica"}, {"type": "filter", "expr": "datum.ccp == CCP"}, {"type": "filter", "expr": "datum.score_prop >1"}, {"type": "formula", "as": "score_prop", "expr": "format((datum.score_prop), '.1f')"}], "values": "[{\"name\":\"dzindrolo\",\"ccp\":\"chamane\",\"practica\":\"apanhadores\",\"score_prop\":20.1889020071},{\"name\":\"dzisolo\",\"ccp\":\"chamane\",\"practica\":\"apanhadores\",\"score_prop\":0.9445100354},{\"name\":\"gihologo\",\"ccp\":\"chamane\",\"practica\":\"apanhadores\",\"score_prop\":2.479338843},{\"name\":\"gingave\",\"ccp\":\"chamane\",\"practica\":\"apanhadores\",\"score_prop\":7.4380165289},{\"name\":\"giredenene\",\"ccp\":\"chamane\",\"practica\":\"apanhadores\",\"score_prop\":0.9445100354},{\"name\":\"makolo\",\"ccp\":\"chamane\",\"practica\":\"apanhadores\",\"score_prop\":5.4309327037},{\"name\":\"mapalo\",\"ccp\":\"chamane\",\"practica\":\"apanhadores\",\"score_prop\":2.2432113341},{\"name\":\"marengue\",\"ccp\":\"chamane\",\"practica\":\"apanhadores\",\"score_prop\":2.1251475797},{\"name\":\"masaba\",\"ccp\":\"chamane\",\"practica\":\"apanhadores\",\"score_prop\":1.0625737898},{\"name\":\"matewo\",\"ccp\":\"chamane\",\"practica\":\"apanhadores\",\"score_prop\":12.8689492326},{\"name\":\"mavandzi\",\"ccp\":\"chamane\",\"practica\":\"apanhadores\",\"score_prop\":13.5773317591},{\"name\":\"mitifa\",\"ccp\":\"chamane\",\"practica\":\"apanhadores\",\"score_prop\":0.826446281},{\"name\":\"mwahaha\",\"ccp\":\"chamane\",\"practica\":\"apanhadores\",\"score_prop\":1.4167650531},{\"name\":\"nhamuele\",\"ccp\":\"chamane\",\"practica\":\"apanhadores\",\"score_prop\":3.7780401417},{\"name\":\"nhamunhe\",\"ccp\":\"chamane\",\"practica\":\"apanhadores\",\"score_prop\":3.1877213695},{\"name\":\"nhanguedwa\",\"ccp\":\"chamane\",\"practica\":\"apanhadores\",\"score_prop\":1.4167650531},{\"name\":\"nhasastani\",\"ccp\":\"chamane\",\"practica\":\"apanhadores\",\"score_prop\":2.0070838253},{\"name\":\"nhatogue\",\"ccp\":\"chamane\",\"practica\":\"apanhadores\",\"score_prop\":1.5348288076},{\"name\":\"nvuma\",\"ccp\":\"chamane\",\"practica\":\"apanhadores\",\"score_prop\":4.0141676505},{\"name\":\"togoma\",\"ccp\":\"chamane\",\"practica\":\"apanhadores\",\"score_prop\":10.1534828808},{\"name\":\"tsanga\",\"ccp\":\"chamane\",\"practica\":\"apanhadores\",\"score_prop\":2.3612750885},{\"name\":\"dzindrolo\",\"ccp\":\"ilha\",\"practica\":\"apanhadores\",\"score_prop\":15.7407407407},{\"name\":\"gihologo\",\"ccp\":\"ilha\",\"practica\":\"apanhadores\",\"score_prop\":0.3968253968},{\"name\":\"giralakhokho\",\"ccp\":\"ilha\",\"practica\":\"apanhadores\",\"score_prop\":0.5291005291},{\"name\":\"giredenene\",\"ccp\":\"ilha\",\"practica\":\"apanhadores\",\"score_prop\":0.0},{\"name\":\"honho\",\"ccp\":\"ilha\",\"practica\":\"apanhadores\",\"score_prop\":0.7936507937},{\"name\":\"mahoma\",\"ccp\":\"ilha\",\"practica\":\"apanhadores\",\"score_prop\":7.0105820106},{\"name\":\"makolo\",\"ccp\":\"ilha\",\"practica\":\"apanhadores\",\"score_prop\":0.2645502646},{\"name\":\"mapalo\",\"ccp\":\"ilha\",\"practica\":\"apanhadores\",\"score_prop\":20.5026455026},{\"name\":\"matewo\",\"ccp\":\"ilha\",\"practica\":\"apanhadores\",\"score_prop\":17.5925925926},{\"name\":\"mavandzi\",\"ccp\":\"ilha\",\"practica\":\"apanhadores\",\"score_prop\":26.7195767196},{\"name\":\"mavionho\",\"ccp\":\"ilha\",\"practica\":\"apanhadores\",\"score_prop\":0.7936507937},{\"name\":\"mihili\",\"ccp\":\"ilha\",\"practica\":\"apanhadores\",\"score_prop\":0.5291005291},{\"name\":\"nhakomi\",\"ccp\":\"ilha\",\"practica\":\"apanhadores\",\"score_prop\":0.1322751323},{\"name\":\"nhakusi\",\"ccp\":\"ilha\",\"practica\":\"apanhadores\",\"score_prop\":0.0},{\"name\":\"nhamunhe\",\"ccp\":\"ilha\",\"practica\":\"apanhadores\",\"score_prop\":4.6296296296},{\"name\":\"nhasastani\",\"ccp\":\"ilha\",\"practica\":\"apanhadores\",\"score_prop\":1.9841269841},{\"name\":\"nvuma\",\"ccp\":\"ilha\",\"practica\":\"apanhadores\",\"score_prop\":0.0},{\"name\":\"simbatsani\",\"ccp\":\"ilha\",\"practica\":\"apanhadores\",\"score_prop\":0.2645502646},{\"name\":\"togoma\",\"ccp\":\"ilha\",\"practica\":\"apanhadores\",\"score_prop\":2.1164021164},{\"name\":\"dzindrolo\",\"ccp\":\"josina_machel\",\"practica\":\"apanhadores\",\"score_prop\":19.6078431373},{\"name\":\"mahoma\",\"ccp\":\"josina_machel\",\"practica\":\"apanhadores\",\"score_prop\":3.431372549},{\"name\":\"mapalo\",\"ccp\":\"josina_machel\",\"practica\":\"apanhadores\",\"score_prop\":28.431372549},{\"name\":\"matewo\",\"ccp\":\"josina_machel\",\"practica\":\"apanhadores\",\"score_prop\":34.8039215686},{\"name\":\"mavandzi\",\"ccp\":\"josina_machel\",\"practica\":\"apanhadores\",\"score_prop\":7.3529411765},{\"name\":\"nhamuele\",\"ccp\":\"josina_machel\",\"practica\":\"apanhadores\",\"score_prop\":2.9411764706},{\"name\":\"nhamunhe\",\"ccp\":\"josina_machel\",\"practica\":\"apanhadores\",\"score_prop\":3.431372549},{\"name\":\"dzindrolo\",\"ccp\":\"madava\",\"practica\":\"apanhadores\",\"score_prop\":19.5402298851},{\"name\":\"gihologo\",\"ccp\":\"madava\",\"practica\":\"apanhadores\",\"score_prop\":3.4482758621},{\"name\":\"gudua\",\"ccp\":\"madava\",\"practica\":\"apanhadores\",\"score_prop\":5.1724137931},{\"name\":\"masaba\",\"ccp\":\"madava\",\"practica\":\"apanhadores\",\"score_prop\":2.2988505747},{\"name\":\"mavandzi\",\"ccp\":\"madava\",\"practica\":\"apanhadores\",\"score_prop\":35.0574712644},{\"name\":\"mitifa\",\"ccp\":\"madava\",\"practica\":\"apanhadores\",\"score_prop\":5.1724137931},{\"name\":\"nhakumbe\",\"ccp\":\"madava\",\"practica\":\"apanhadores\",\"score_prop\":1.1494252874},{\"name\":\"nhanguedwa\",\"ccp\":\"madava\",\"practica\":\"apanhadores\",\"score_prop\":26.4367816092},{\"name\":\"nhatogue\",\"ccp\":\"madava\",\"practica\":\"apanhadores\",\"score_prop\":1.724137931},{\"name\":\"dzindrolo\",\"ccp\":\"marrambone\",\"practica\":\"apanhadores\",\"score_prop\":26.5432098765},{\"name\":\"mapalo\",\"ccp\":\"marrambone\",\"practica\":\"apanhadores\",\"score_prop\":4.3209876543},{\"name\":\"matewo\",\"ccp\":\"marrambone\",\"practica\":\"apanhadores\",\"score_prop\":15.4320987654},{\"name\":\"mavandzi\",\"ccp\":\"marrambone\",\"practica\":\"apanhadores\",\"score_prop\":21.6049382716},{\"name\":\"nhamunhe\",\"ccp\":\"marrambone\",\"practica\":\"apanhadores\",\"score_prop\":16.049382716},{\"name\":\"nhasastani\",\"ccp\":\"marrambone\",\"practica\":\"apanhadores\",\"score_prop\":7.4074074074},{\"name\":\"togoma\",\"ccp\":\"marrambone\",\"practica\":\"apanhadores\",\"score_prop\":8.6419753086},{\"name\":\"dzindrolo\",\"ccp\":\"morrumbene\",\"practica\":\"apanhadores\",\"score_prop\":16.049382716},{\"name\":\"gingave\",\"ccp\":\"morrumbene\",\"practica\":\"apanhadores\",\"score_prop\":4.9382716049},{\"name\":\"mahutu\",\"ccp\":\"morrumbene\",\"practica\":\"apanhadores\",\"score_prop\":9.1358024691},{\"name\":\"matewo\",\"ccp\":\"morrumbene\",\"practica\":\"apanhadores\",\"score_prop\":2.2222222222},{\"name\":\"mavandzi\",\"ccp\":\"morrumbene\",\"practica\":\"apanhadores\",\"score_prop\":8.3950617284},{\"name\":\"mikaki\",\"ccp\":\"morrumbene\",\"practica\":\"apanhadores\",\"score_prop\":1.7283950617},{\"name\":\"mitifa\",\"ccp\":\"morrumbene\",\"practica\":\"apanhadores\",\"score_prop\":2.962962963},{\"name\":\"nhanguedwa\",\"ccp\":\"morrumbene\",\"practica\":\"apanhadores\",\"score_prop\":34.3209876543},{\"name\":\"nhatogue\",\"ccp\":\"morrumbene\",\"practica\":\"apanhadores\",\"score_prop\":7.4074074074},{\"name\":\"simbatsani\",\"ccp\":\"morrumbene\",\"practica\":\"apanhadores\",\"score_prop\":1.4814814815},{\"name\":\"togoma\",\"ccp\":\"morrumbene\",\"practica\":\"apanhadores\",\"score_prop\":11.3580246914},{\"name\":\"dzindrolo\",\"ccp\":\"mucucune\",\"practica\":\"apanhadores\",\"score_prop\":27.1739130435},{\"name\":\"mahoma\",\"ccp\":\"mucucune\",\"practica\":\"apanhadores\",\"score_prop\":7.6086956522},{\"name\":\"mavandzi\",\"ccp\":\"mucucune\",\"practica\":\"apanhadores\",\"score_prop\":39.1304347826},{\"name\":\"simbatsani\",\"ccp\":\"mucucune\",\"practica\":\"apanhadores\",\"score_prop\":8.6956521739},{\"name\":\"togoma\",\"ccp\":\"mucucune\",\"practica\":\"apanhadores\",\"score_prop\":17.3913043478},{\"name\":\"dzindrolo\",\"ccp\":\"nhamaxaxa\",\"practica\":\"apanhadores\",\"score_prop\":50.5882352941},{\"name\":\"nhamunhe\",\"ccp\":\"nhamaxaxa\",\"practica\":\"apanhadores\",\"score_prop\":18.8235294118},{\"name\":\"nhandrendre\",\"ccp\":\"nhamaxaxa\",\"practica\":\"apanhadores\",\"score_prop\":8.2352941176},{\"name\":\"nhasastani\",\"ccp\":\"nhamaxaxa\",\"practica\":\"apanhadores\",\"score_prop\":15.2941176471},{\"name\":\"simbatsani\",\"ccp\":\"nhamaxaxa\",\"practica\":\"apanhadores\",\"score_prop\":7.0588235294},{\"name\":\"dzindrolo\",\"ccp\":\"nhampossa\",\"practica\":\"apanhadores\",\"score_prop\":33.6633663366},{\"name\":\"mavandzi\",\"ccp\":\"nhampossa\",\"practica\":\"apanhadores\",\"score_prop\":15.8415841584},{\"name\":\"nhakumbe\",\"ccp\":\"nhampossa\",\"practica\":\"apanhadores\",\"score_prop\":13.8613861386},{\"name\":\"nhatogue\",\"ccp\":\"nhampossa\",\"practica\":\"apanhadores\",\"score_prop\":5.9405940594},{\"name\":\"togoma\",\"ccp\":\"nhampossa\",\"practica\":\"apanhadores\",\"score_prop\":23.7623762376},{\"name\":\"tsanga\",\"ccp\":\"nhampossa\",\"practica\":\"apanhadores\",\"score_prop\":6.9306930693},{\"name\":\"dzindrolo\",\"ccp\":\"nhamua\",\"practica\":\"apanhadores\",\"score_prop\":20.6647398844},{\"name\":\"gingave\",\"ccp\":\"nhamua\",\"practica\":\"apanhadores\",\"score_prop\":1.1560693642},{\"name\":\"mahoma\",\"ccp\":\"nhamua\",\"practica\":\"apanhadores\",\"score_prop\":13.7283236994},{\"name\":\"makolo\",\"ccp\":\"nhamua\",\"practica\":\"apanhadores\",\"score_prop\":3.0346820809},{\"name\":\"mapalo\",\"ccp\":\"nhamua\",\"practica\":\"apanhadores\",\"score_prop\":16.3294797688},{\"name\":\"marengue\",\"ccp\":\"nhamua\",\"practica\":\"apanhadores\",\"score_prop\":1.0115606936},{\"name\":\"matewo\",\"ccp\":\"nhamua\",\"practica\":\"apanhadores\",\"score_prop\":22.5433526012},{\"name\":\"mavandzi\",\"ccp\":\"nhamua\",\"practica\":\"apanhadores\",\"score_prop\":9.5375722543},{\"name\":\"nhamunhe\",\"ccp\":\"nhamua\",\"practica\":\"apanhadores\",\"score_prop\":8.0924855491},{\"name\":\"nhatogue\",\"ccp\":\"nhamua\",\"practica\":\"apanhadores\",\"score_prop\":0.289017341},{\"name\":\"nvuma\",\"ccp\":\"nhamua\",\"practica\":\"apanhadores\",\"score_prop\":1.0115606936},{\"name\":\"simbatsani\",\"ccp\":\"nhamua\",\"practica\":\"apanhadores\",\"score_prop\":1.0115606936},{\"name\":\"togoma\",\"ccp\":\"nhamua\",\"practica\":\"apanhadores\",\"score_prop\":1.5895953757},{\"name\":\"dzindrolo\",\"ccp\":\"njuga\",\"practica\":\"apanhadores\",\"score_prop\":25.0},{\"name\":\"giralakhokho\",\"ccp\":\"njuga\",\"practica\":\"apanhadores\",\"score_prop\":7.1428571429},{\"name\":\"giredenene\",\"ccp\":\"njuga\",\"practica\":\"apanhadores\",\"score_prop\":1.0714285714},{\"name\":\"guikhokoroma\",\"ccp\":\"njuga\",\"practica\":\"apanhadores\",\"score_prop\":10.0},{\"name\":\"mapalo\",\"ccp\":\"njuga\",\"practica\":\"apanhadores\",\"score_prop\":5.0},{\"name\":\"masaba\",\"ccp\":\"njuga\",\"practica\":\"apanhadores\",\"score_prop\":6.0714285714},{\"name\":\"mavandzi\",\"ccp\":\"njuga\",\"practica\":\"apanhadores\",\"score_prop\":8.9285714286},{\"name\":\"nhamuele\",\"ccp\":\"njuga\",\"practica\":\"apanhadores\",\"score_prop\":1.4285714286},{\"name\":\"nhamunhe\",\"ccp\":\"njuga\",\"practica\":\"apanhadores\",\"score_prop\":10.3571428571},{\"name\":\"nhasastani\",\"ccp\":\"njuga\",\"practica\":\"apanhadores\",\"score_prop\":5.3571428571},{\"name\":\"nvuma\",\"ccp\":\"njuga\",\"practica\":\"apanhadores\",\"score_prop\":2.1428571429},{\"name\":\"simbatsani\",\"ccp\":\"njuga\",\"practica\":\"apanhadores\",\"score_prop\":12.1428571429},{\"name\":\"togoma\",\"ccp\":\"njuga\",\"practica\":\"apanhadores\",\"score_prop\":3.9285714286},{\"name\":\"tsanga\",\"ccp\":\"njuga\",\"practica\":\"apanhadores\",\"score_prop\":1.4285714286},{\"name\":\"dzindrolo\",\"ccp\":\"sahane\",\"practica\":\"apanhadores\",\"score_prop\":33.3333333333},{\"name\":\"mahoma\",\"ccp\":\"sahane\",\"practica\":\"apanhadores\",\"score_prop\":7.619047619},{\"name\":\"matewo\",\"ccp\":\"sahane\",\"practica\":\"apanhadores\",\"score_prop\":13.3333333333},{\"name\":\"nhamunhe\",\"ccp\":\"sahane\",\"practica\":\"apanhadores\",\"score_prop\":15.2380952381},{\"name\":\"simbatsani\",\"ccp\":\"sahane\",\"practica\":\"apanhadores\",\"score_prop\":23.8095238095},{\"name\":\"tsanga\",\"ccp\":\"sahane\",\"practica\":\"apanhadores\",\"score_prop\":6.6666666667},{\"name\":\"masaba\",\"ccp\":\"kuguana\",\"practica\":\"apanhadores\",\"score_prop\":14.0625},{\"name\":\"mavandzi\",\"ccp\":\"kuguana\",\"practica\":\"apanhadores\",\"score_prop\":10.9375},{\"name\":\"nhakumbe\",\"ccp\":\"kuguana\",\"practica\":\"apanhadores\",\"score_prop\":12.5},{\"name\":\"nhanguedwa\",\"ccp\":\"kuguana\",\"practica\":\"apanhadores\",\"score_prop\":10.9375},{\"name\":\"nhatogue\",\"ccp\":\"kuguana\",\"practica\":\"apanhadores\",\"score_prop\":29.6875},{\"name\":\"simbatsani\",\"ccp\":\"kuguana\",\"practica\":\"apanhadores\",\"score_prop\":7.8125},{\"name\":\"togoma\",\"ccp\":\"kuguana\",\"practica\":\"apanhadores\",\"score_prop\":14.0625},{\"name\":\"dzindrolo\",\"ccp\":\"baia\",\"practica\":\"apanhadores\",\"score_prop\":20.8719619143},{\"name\":\"dzisolo\",\"ccp\":\"baia\",\"practica\":\"apanhadores\",\"score_prop\":0.2004510148},{\"name\":\"gihologo\",\"ccp\":\"baia\",\"practica\":\"apanhadores\",\"score_prop\":0.8519168128},{\"name\":\"gingave\",\"ccp\":\"baia\",\"practica\":\"apanhadores\",\"score_prop\":2.2801302932},{\"name\":\"giralakhokho\",\"ccp\":\"baia\",\"practica\":\"apanhadores\",\"score_prop\":0.6013530443},{\"name\":\"giredenene\",\"ccp\":\"baia\",\"practica\":\"apanhadores\",\"score_prop\":0.2756201453},{\"name\":\"gudua\",\"ccp\":\"baia\",\"practica\":\"apanhadores\",\"score_prop\":0.2255073916},{\"name\":\"guikhokoroma\",\"ccp\":\"baia\",\"practica\":\"apanhadores\",\"score_prop\":0.7015785517},{\"name\":\"honho\",\"ccp\":\"baia\",\"practica\":\"apanhadores\",\"score_prop\":0.1503382611},{\"name\":\"mahoma\",\"ccp\":\"baia\",\"practica\":\"apanhadores\",\"score_prop\":4.2595840641},{\"name\":\"mahutu\",\"ccp\":\"baia\",\"practica\":\"apanhadores\",\"score_prop\":0.9270859434},{\"name\":\"makolo\",\"ccp\":\"baia\",\"practica\":\"apanhadores\",\"score_prop\":1.7288900025},{\"name\":\"mapalo\",\"ccp\":\"baia\",\"practica\":\"apanhadores\",\"score_prop\":9.1706339263},{\"name\":\"marengue\",\"ccp\":\"baia\",\"practica\":\"apanhadores\",\"score_prop\":0.6264094212},{\"name\":\"masaba\",\"ccp\":\"baia\",\"practica\":\"apanhadores\",\"score_prop\":0.9771986971},{\"name\":\"matewo\",\"ccp\":\"baia\",\"practica\":\"apanhadores\",\"score_prop\":12.9541468304},{\"name\":\"mavandzi\",\"ccp\":\"baia\",\"practica\":\"apanhadores\",\"score_prop\":15.3345026309},{\"name\":\"mavionho\",\"ccp\":\"baia\",\"practica\":\"apanhadores\",\"score_prop\":0.1503382611},{\"name\":\"mihili\",\"ccp\":\"baia\",\"practica\":\"apanhadores\",\"score_prop\":0.1002255074},{\"name\":\"mikaki\",\"ccp\":\"baia\",\"practica\":\"apanhadores\",\"score_prop\":0.1753946379},{\"name\":\"mitifa\",\"ccp\":\"baia\",\"practica\":\"apanhadores\",\"score_prop\":0.7015785517},{\"name\":\"mwahaha\",\"ccp\":\"baia\",\"practica\":\"apanhadores\",\"score_prop\":0.3006765222},{\"name\":\"nhakomi\",\"ccp\":\"baia\",\"practica\":\"apanhadores\",\"score_prop\":0.0250563768},{\"name\":\"nhakumbe\",\"ccp\":\"baia\",\"practica\":\"apanhadores\",\"score_prop\":0.6013530443},{\"name\":\"nhakusi\",\"ccp\":\"baia\",\"practica\":\"apanhadores\",\"score_prop\":0.0},{\"name\":\"nhamuele\",\"ccp\":\"baia\",\"practica\":\"apanhadores\",\"score_prop\":1.0523678276},{\"name\":\"nhamunhe\",\"ccp\":\"baia\",\"practica\":\"apanhadores\",\"score_prop\":5.3119518918},{\"name\":\"nhandrendre\",\"ccp\":\"baia\",\"practica\":\"apanhadores\",\"score_prop\":0.1753946379},{\"name\":\"nhanguedwa\",\"ccp\":\"baia\",\"practica\":\"apanhadores\",\"score_prop\":5.111500877},{\"name\":\"nhasastani\",\"ccp\":\"baia\",\"practica\":\"apanhadores\",\"score_prop\":1.804059133},{\"name\":\"nhatogue\",\"ccp\":\"baia\",\"practica\":\"apanhadores\",\"score_prop\":1.8291155099},{\"name\":\"nvuma\",\"ccp\":\"baia\",\"practica\":\"apanhadores\",\"score_prop\":1.1776497119},{\"name\":\"simbatsani\",\"ccp\":\"baia\",\"practica\":\"apanhadores\",\"score_prop\":2.3302430469},{\"name\":\"togoma\",\"ccp\":\"baia\",\"practica\":\"apanhadores\",\"score_prop\":6.0636431972},{\"name\":\"tsanga\",\"ccp\":\"baia\",\"practica\":\"apanhadores\",\"score_prop\":0.9521423202},{\"name\":\"49\",\"ccp\":\"morrumbene\",\"practica\":\"pescadores\",\"score_prop\":0.4213483146},{\"name\":\"carapo\",\"ccp\":\"morrumbene\",\"practica\":\"pescadores\",\"score_prop\":4.9859550562},{\"name\":\"dzindrolo\",\"ccp\":\"morrumbene\",\"practica\":\"pescadores\",\"score_prop\":7.7247191011},{\"name\":\"dzipata\",\"ccp\":\"morrumbene\",\"practica\":\"pescadores\",\"score_prop\":3.7219101124},{\"name\":\"gidzuani\",\"ccp\":\"morrumbene\",\"practica\":\"pescadores\",\"score_prop\":0.2106741573},{\"name\":\"gihologo\",\"ccp\":\"morrumbene\",\"practica\":\"pescadores\",\"score_prop\":3.0898876404},{\"name\":\"gitongwe\",\"ccp\":\"morrumbene\",\"practica\":\"pescadores\",\"score_prop\":3.2303370787},{\"name\":\"gudua\",\"ccp\":\"morrumbene\",\"practica\":\"pescadores\",\"score_prop\":4.4241573034},{\"name\":\"honho\",\"ccp\":\"morrumbene\",\"practica\":\"pescadores\",\"score_prop\":7.5140449438},{\"name\":\"kolokolo\",\"ccp\":\"morrumbene\",\"practica\":\"pescadores\",\"score_prop\":0.8426966292},{\"name\":\"kuku\",\"ccp\":\"morrumbene\",\"practica\":\"pescadores\",\"score_prop\":0.4213483146},{\"name\":\"lidume\",\"ccp\":\"morrumbene\",\"practica\":\"pescadores\",\"score_prop\":1.6151685393},{\"name\":\"likerere\",\"ccp\":\"morrumbene\",\"practica\":\"pescadores\",\"score_prop\":0.8426966292},{\"name\":\"magumba\",\"ccp\":\"morrumbene\",\"practica\":\"pescadores\",\"score_prop\":0.2106741573},{\"name\":\"masaba\",\"ccp\":\"morrumbene\",\"practica\":\"pescadores\",\"score_prop\":4.0028089888},{\"name\":\"mavandzi\",\"ccp\":\"morrumbene\",\"practica\":\"pescadores\",\"score_prop\":13.6235955056},{\"name\":\"mavionho\",\"ccp\":\"morrumbene\",\"practica\":\"pescadores\",\"score_prop\":4.4943820225},{\"name\":\"mbabe\",\"ccp\":\"morrumbene\",\"practica\":\"pescadores\",\"score_prop\":3.1601123596},{\"name\":\"mifiti\",\"ccp\":\"morrumbene\",\"practica\":\"pescadores\",\"score_prop\":2.0365168539},{\"name\":\"mihili\",\"ccp\":\"morrumbene\",\"practica\":\"pescadores\",\"score_prop\":7.4438202247},{\"name\":\"nhabugue\",\"ccp\":\"morrumbene\",\"practica\":\"pescadores\",\"score_prop\":1.0533707865},{\"name\":\"nhakomani\",\"ccp\":\"morrumbene\",\"practica\":\"pescadores\",\"score_prop\":0.2106741573},{\"name\":\"nhanguedwa\",\"ccp\":\"morrumbene\",\"practica\":\"pescadores\",\"score_prop\":0.3511235955},{\"name\":\"nharongue\",\"ccp\":\"morrumbene\",\"practica\":\"pescadores\",\"score_prop\":2.106741573},{\"name\":\"salani\",\"ccp\":\"morrumbene\",\"practica\":\"pescadores\",\"score_prop\":1.6853932584},{\"name\":\"sigulula\",\"ccp\":\"morrumbene\",\"practica\":\"pescadores\",\"score_prop\":0.8426966292},{\"name\":\"tendre\",\"ccp\":\"morrumbene\",\"practica\":\"pescadores\",\"score_prop\":3.0196629213},{\"name\":\"togoma\",\"ccp\":\"morrumbene\",\"practica\":\"pescadores\",\"score_prop\":0.4213483146},{\"name\":\"tsakanhani\",\"ccp\":\"morrumbene\",\"practica\":\"pescadores\",\"score_prop\":2.7387640449},{\"name\":\"tsava\",\"ccp\":\"morrumbene\",\"practica\":\"pescadores\",\"score_prop\":9.3398876404},{\"name\":\"tsongua\",\"ccp\":\"morrumbene\",\"practica\":\"pescadores\",\"score_prop\":2.1769662921},{\"name\":\"xereua\",\"ccp\":\"morrumbene\",\"practica\":\"pescadores\",\"score_prop\":2.0365168539},{\"name\":\"carapo\",\"ccp\":\"ilha\",\"practica\":\"pescadores\",\"score_prop\":1.9801980198},{\"name\":\"dzindrolo\",\"ccp\":\"ilha\",\"practica\":\"pescadores\",\"score_prop\":2.7722772277},{\"name\":\"dzipata\",\"ccp\":\"ilha\",\"practica\":\"pescadores\",\"score_prop\":9.3069306931},{\"name\":\"gihologo\",\"ccp\":\"ilha\",\"practica\":\"pescadores\",\"score_prop\":1.1881188119},{\"name\":\"gitongwe\",\"ccp\":\"ilha\",\"practica\":\"pescadores\",\"score_prop\":1.1881188119},{\"name\":\"gudua\",\"ccp\":\"ilha\",\"practica\":\"pescadores\",\"score_prop\":0.7920792079},{\"name\":\"honho\",\"ccp\":\"ilha\",\"practica\":\"pescadores\",\"score_prop\":1.1881188119},{\"name\":\"korea\",\"ccp\":\"ilha\",\"practica\":\"pescadores\",\"score_prop\":2.7722772277},{\"name\":\"kuku\",\"ccp\":\"ilha\",\"practica\":\"pescadores\",\"score_prop\":3.1683168317},{\"name\":\"mahoma\",\"ccp\":\"ilha\",\"practica\":\"pescadores\",\"score_prop\":0.198019802},{\"name\":\"makolo\",\"ccp\":\"ilha\",\"practica\":\"pescadores\",\"score_prop\":0.396039604},{\"name\":\"mapalo\",\"ccp\":\"ilha\",\"practica\":\"pescadores\",\"score_prop\":0.198019802},{\"name\":\"marengue\",\"ccp\":\"ilha\",\"practica\":\"pescadores\",\"score_prop\":0.198019802},{\"name\":\"matewo\",\"ccp\":\"ilha\",\"practica\":\"pescadores\",\"score_prop\":1.7821782178},{\"name\":\"mavandzi\",\"ccp\":\"ilha\",\"practica\":\"pescadores\",\"score_prop\":23.3663366337},{\"name\":\"mavionho\",\"ccp\":\"ilha\",\"practica\":\"pescadores\",\"score_prop\":5.5445544554},{\"name\":\"mbabe\",\"ccp\":\"ilha\",\"practica\":\"pescadores\",\"score_prop\":5.3465346535},{\"name\":\"mifiti\",\"ccp\":\"ilha\",\"practica\":\"pescadores\",\"score_prop\":1.1881188119},{\"name\":\"mihili\",\"ccp\":\"ilha\",\"practica\":\"pescadores\",\"score_prop\":11.4851485149},{\"name\":\"nhabugue\",\"ccp\":\"ilha\",\"practica\":\"pescadores\",\"score_prop\":4.3564356436},{\"name\":\"salani\",\"ccp\":\"ilha\",\"practica\":\"pescadores\",\"score_prop\":7.1287128713},{\"name\":\"sigulula\",\"ccp\":\"ilha\",\"practica\":\"pescadores\",\"score_prop\":5.7425742574},{\"name\":\"sololo\",\"ccp\":\"ilha\",\"practica\":\"pescadores\",\"score_prop\":0.5940594059},{\"name\":\"tendre\",\"ccp\":\"ilha\",\"practica\":\"pescadores\",\"score_prop\":4.1584158416},{\"name\":\"tsogola\",\"ccp\":\"ilha\",\"practica\":\"pescadores\",\"score_prop\":1.1881188119},{\"name\":\"tsongua\",\"ccp\":\"ilha\",\"practica\":\"pescadores\",\"score_prop\":1.7821782178},{\"name\":\"xereua\",\"ccp\":\"ilha\",\"practica\":\"pescadores\",\"score_prop\":0.9900990099},{\"name\":\"carapo\",\"ccp\":\"josina_machel\",\"practica\":\"pescadores\",\"score_prop\":11.8181818182},{\"name\":\"dzindrolo\",\"ccp\":\"josina_machel\",\"practica\":\"pescadores\",\"score_prop\":2.7272727273},{\"name\":\"dzipata\",\"ccp\":\"josina_machel\",\"practica\":\"pescadores\",\"score_prop\":5.1515151515},{\"name\":\"gudua\",\"ccp\":\"josina_machel\",\"practica\":\"pescadores\",\"score_prop\":5.4545454545},{\"name\":\"honho\",\"ccp\":\"josina_machel\",\"practica\":\"pescadores\",\"score_prop\":3.9393939394},{\"name\":\"kolokolo\",\"ccp\":\"josina_machel\",\"practica\":\"pescadores\",\"score_prop\":2.4242424242},{\"name\":\"korea\",\"ccp\":\"josina_machel\",\"practica\":\"pescadores\",\"score_prop\":2.1212121212},{\"name\":\"kuku\",\"ccp\":\"josina_machel\",\"practica\":\"pescadores\",\"score_prop\":1.2121212121},{\"name\":\"makolo\",\"ccp\":\"josina_machel\",\"practica\":\"pescadores\",\"score_prop\":2.4242424242},{\"name\":\"mapalo\",\"ccp\":\"josina_machel\",\"practica\":\"pescadores\",\"score_prop\":2.4242424242},{\"name\":\"matewo\",\"ccp\":\"josina_machel\",\"practica\":\"pescadores\",\"score_prop\":1.8181818182},{\"name\":\"mavionho\",\"ccp\":\"josina_machel\",\"practica\":\"pescadores\",\"score_prop\":14.5454545455},{\"name\":\"mbabe\",\"ccp\":\"josina_machel\",\"practica\":\"pescadores\",\"score_prop\":0.6060606061},{\"name\":\"mihili\",\"ccp\":\"josina_machel\",\"practica\":\"pescadores\",\"score_prop\":12.1212121212},{\"name\":\"salani\",\"ccp\":\"josina_machel\",\"practica\":\"pescadores\",\"score_prop\":11.8181818182},{\"name\":\"sigulula\",\"ccp\":\"josina_machel\",\"practica\":\"pescadores\",\"score_prop\":7.2727272727},{\"name\":\"sololo\",\"ccp\":\"josina_machel\",\"practica\":\"pescadores\",\"score_prop\":2.4242424242},{\"name\":\"tendre\",\"ccp\":\"josina_machel\",\"practica\":\"pescadores\",\"score_prop\":4.2424242424},{\"name\":\"tsakanhani\",\"ccp\":\"josina_machel\",\"practica\":\"pescadores\",\"score_prop\":0.9090909091},{\"name\":\"tsongua\",\"ccp\":\"josina_machel\",\"practica\":\"pescadores\",\"score_prop\":1.8181818182},{\"name\":\"xereua\",\"ccp\":\"josina_machel\",\"practica\":\"pescadores\",\"score_prop\":2.7272727273},{\"name\":\"carapo\",\"ccp\":\"kuguana\",\"practica\":\"pescadores\",\"score_prop\":0.974025974},{\"name\":\"dzindrolo\",\"ccp\":\"kuguana\",\"practica\":\"pescadores\",\"score_prop\":5.9253246753},{\"name\":\"dzipata\",\"ccp\":\"kuguana\",\"practica\":\"pescadores\",\"score_prop\":3.4902597403},{\"name\":\"gidagianha\",\"ccp\":\"kuguana\",\"practica\":\"pescadores\",\"score_prop\":0.487012987},{\"name\":\"gihologo\",\"ccp\":\"kuguana\",\"practica\":\"pescadores\",\"score_prop\":4.8701298701},{\"name\":\"gitongwe\",\"ccp\":\"kuguana\",\"practica\":\"pescadores\",\"score_prop\":2.1915584416},{\"name\":\"gudua\",\"ccp\":\"kuguana\",\"practica\":\"pescadores\",\"score_prop\":7.4675324675},{\"name\":\"honho\",\"ccp\":\"kuguana\",\"practica\":\"pescadores\",\"score_prop\":6.4935064935},{\"name\":\"kolokolo\",\"ccp\":\"kuguana\",\"practica\":\"pescadores\",\"score_prop\":0.8116883117},{\"name\":\"livandrevandre\",\"ccp\":\"kuguana\",\"practica\":\"pescadores\",\"score_prop\":0.1623376623},{\"name\":\"magumba\",\"ccp\":\"kuguana\",\"practica\":\"pescadores\",\"score_prop\":2.1915584416},{\"name\":\"masaba\",\"ccp\":\"kuguana\",\"practica\":\"pescadores\",\"score_prop\":12.7435064935},{\"name\":\"mavandzi\",\"ccp\":\"kuguana\",\"practica\":\"pescadores\",\"score_prop\":19.1558441558},{\"name\":\"mavionho\",\"ccp\":\"kuguana\",\"practica\":\"pescadores\",\"score_prop\":1.8668831169},{\"name\":\"mbabe\",\"ccp\":\"kuguana\",\"practica\":\"pescadores\",\"score_prop\":0.8116883117},{\"name\":\"mifiti\",\"ccp\":\"kuguana\",\"practica\":\"pescadores\",\"score_prop\":2.0292207792},{\"name\":\"mihili\",\"ccp\":\"kuguana\",\"practica\":\"pescadores\",\"score_prop\":7.9545454545},{\"name\":\"nani\",\"ccp\":\"kuguana\",\"practica\":\"pescadores\",\"score_prop\":0.2435064935},{\"name\":\"nhakomani\",\"ccp\":\"kuguana\",\"practica\":\"pescadores\",\"score_prop\":3.9772727273},{\"name\":\"nharongue\",\"ccp\":\"kuguana\",\"practica\":\"pescadores\",\"score_prop\":1.7045454545},{\"name\":\"nhatogue\",\"ccp\":\"kuguana\",\"practica\":\"pescadores\",\"score_prop\":0.2435064935},{\"name\":\"salani\",\"ccp\":\"kuguana\",\"practica\":\"pescadores\",\"score_prop\":4.7077922078},{\"name\":\"sardinha\",\"ccp\":\"kuguana\",\"practica\":\"pescadores\",\"score_prop\":0.5681818182},{\"name\":\"sigulula\",\"ccp\":\"kuguana\",\"practica\":\"pescadores\",\"score_prop\":2.5974025974},{\"name\":\"sikwalala\",\"ccp\":\"kuguana\",\"practica\":\"pescadores\",\"score_prop\":0.2435064935},{\"name\":\"sololo\",\"ccp\":\"kuguana\",\"practica\":\"pescadores\",\"score_prop\":0.487012987},{\"name\":\"tendre\",\"ccp\":\"kuguana\",\"practica\":\"pescadores\",\"score_prop\":0.6493506494},{\"name\":\"togoma\",\"ccp\":\"kuguana\",\"practica\":\"pescadores\",\"score_prop\":0.1623376623},{\"name\":\"tsakanhani\",\"ccp\":\"kuguana\",\"practica\":\"pescadores\",\"score_prop\":0.6493506494},{\"name\":\"tsava\",\"ccp\":\"kuguana\",\"practica\":\"pescadores\",\"score_prop\":0.8928571429},{\"name\":\"tsongua\",\"ccp\":\"kuguana\",\"practica\":\"pescadores\",\"score_prop\":0.487012987},{\"name\":\"xereua\",\"ccp\":\"kuguana\",\"practica\":\"pescadores\",\"score_prop\":2.7597402597},{\"name\":\"carapo\",\"ccp\":\"madava\",\"practica\":\"pescadores\",\"score_prop\":3.7997587455},{\"name\":\"dzindrolo\",\"ccp\":\"madava\",\"practica\":\"pescadores\",\"score_prop\":7.056694813},{\"name\":\"dzipata\",\"ccp\":\"madava\",\"practica\":\"pescadores\",\"score_prop\":5.4885404101},{\"name\":\"gihologo\",\"ccp\":\"madava\",\"practica\":\"pescadores\",\"score_prop\":11.8214716526},{\"name\":\"gingave\",\"ccp\":\"madava\",\"practica\":\"pescadores\",\"score_prop\":0.0603136309},{\"name\":\"gitongwe\",\"ccp\":\"madava\",\"practica\":\"pescadores\",\"score_prop\":0.9650180941},{\"name\":\"gudua\",\"ccp\":\"madava\",\"practica\":\"pescadores\",\"score_prop\":1.4475271411},{\"name\":\"honho\",\"ccp\":\"madava\",\"practica\":\"pescadores\",\"score_prop\":0.482509047},{\"name\":\"kolokolo\",\"ccp\":\"madava\",\"practica\":\"pescadores\",\"score_prop\":0.1206272618},{\"name\":\"lidume\",\"ccp\":\"madava\",\"practica\":\"pescadores\",\"score_prop\":0.3015681544},{\"name\":\"magumba\",\"ccp\":\"madava\",\"practica\":\"pescadores\",\"score_prop\":3.2569360676},{\"name\":\"masaba\",\"ccp\":\"madava\",\"practica\":\"pescadores\",\"score_prop\":15.6212303981},{\"name\":\"mavandzi\",\"ccp\":\"madava\",\"practica\":\"pescadores\",\"score_prop\":24.3667068758},{\"name\":\"mavionho\",\"ccp\":\"madava\",\"practica\":\"pescadores\",\"score_prop\":3.6791314837},{\"name\":\"mbabe\",\"ccp\":\"madava\",\"practica\":\"pescadores\",\"score_prop\":0.1206272618},{\"name\":\"mifiti\",\"ccp\":\"madava\",\"practica\":\"pescadores\",\"score_prop\":1.5681544029},{\"name\":\"mihili\",\"ccp\":\"madava\",\"practica\":\"pescadores\",\"score_prop\":4.5838359469},{\"name\":\"mitifa\",\"ccp\":\"madava\",\"practica\":\"pescadores\",\"score_prop\":1.5681544029},{\"name\":\"nani\",\"ccp\":\"madava\",\"practica\":\"pescadores\",\"score_prop\":0.6634499397},{\"name\":\"nhabugue\",\"ccp\":\"madava\",\"practica\":\"pescadores\",\"score_prop\":0.1206272618},{\"name\":\"nhakomani\",\"ccp\":\"madava\",\"practica\":\"pescadores\",\"score_prop\":2.1109770808},{\"name\":\"nharongue\",\"ccp\":\"madava\",\"practica\":\"pescadores\",\"score_prop\":4.041013269},{\"name\":\"salani\",\"ccp\":\"madava\",\"practica\":\"pescadores\",\"score_prop\":1.6284680338},{\"name\":\"sardinha\",\"ccp\":\"madava\",\"practica\":\"pescadores\",\"score_prop\":0.3618817853},{\"name\":\"sigulula\",\"ccp\":\"madava\",\"practica\":\"pescadores\",\"score_prop\":1.4475271411},{\"name\":\"sikwalala\",\"ccp\":\"madava\",\"practica\":\"pescadores\",\"score_prop\":0.0603136309},{\"name\":\"sololo\",\"ccp\":\"madava\",\"practica\":\"pescadores\",\"score_prop\":0.1809408926},{\"name\":\"tendre\",\"ccp\":\"madava\",\"practica\":\"pescadores\",\"score_prop\":0.7840772014},{\"name\":\"tsava\",\"ccp\":\"madava\",\"practica\":\"pescadores\",\"score_prop\":1.9300361882},{\"name\":\"xereua\",\"ccp\":\"madava\",\"practica\":\"pescadores\",\"score_prop\":0.3618817853},{\"name\":\"carapo\",\"ccp\":\"mucucune\",\"practica\":\"pescadores\",\"score_prop\":3.196347032},{\"name\":\"dzindrolo\",\"ccp\":\"mucucune\",\"practica\":\"pescadores\",\"score_prop\":4.5662100457},{\"name\":\"dzipata\",\"ccp\":\"mucucune\",\"practica\":\"pescadores\",\"score_prop\":1.8264840183},{\"name\":\"gitongwe\",\"ccp\":\"mucucune\",\"practica\":\"pescadores\",\"score_prop\":3.6529680365},{\"name\":\"kuku\",\"ccp\":\"mucucune\",\"practica\":\"pescadores\",\"score_prop\":1.3698630137},{\"name\":\"likerere\",\"ccp\":\"mucucune\",\"practica\":\"pescadores\",\"score_prop\":2.2831050228},{\"name\":\"mavandzi\",\"ccp\":\"mucucune\",\"practica\":\"pescadores\",\"score_prop\":4.1095890411},{\"name\":\"mavionho\",\"ccp\":\"mucucune\",\"practica\":\"pescadores\",\"score_prop\":12.3287671233},{\"name\":\"mbabe\",\"ccp\":\"mucucune\",\"practica\":\"pescadores\",\"score_prop\":5.4794520548},{\"name\":\"mihili\",\"ccp\":\"mucucune\",\"practica\":\"pescadores\",\"score_prop\":18.2648401826},{\"name\":\"ngee\",\"ccp\":\"mucucune\",\"practica\":\"pescadores\",\"score_prop\":4.1095890411},{\"name\":\"nhabugue\",\"ccp\":\"mucucune\",\"practica\":\"pescadores\",\"score_prop\":3.196347032},{\"name\":\"salani\",\"ccp\":\"mucucune\",\"practica\":\"pescadores\",\"score_prop\":18.7214611872},{\"name\":\"sardinha\",\"ccp\":\"mucucune\",\"practica\":\"pescadores\",\"score_prop\":1.8264840183},{\"name\":\"sigulula\",\"ccp\":\"mucucune\",\"practica\":\"pescadores\",\"score_prop\":11.4155251142},{\"name\":\"tsongua\",\"ccp\":\"mucucune\",\"practica\":\"pescadores\",\"score_prop\":1.8264840183},{\"name\":\"xereua\",\"ccp\":\"mucucune\",\"practica\":\"pescadores\",\"score_prop\":1.8264840183},{\"name\":\"carapo\",\"ccp\":\"nhamaxaxa\",\"practica\":\"pescadores\",\"score_prop\":6.5306122449},{\"name\":\"dzindrolo\",\"ccp\":\"nhamaxaxa\",\"practica\":\"pescadores\",\"score_prop\":3.6734693878},{\"name\":\"dzipata\",\"ccp\":\"nhamaxaxa\",\"practica\":\"pescadores\",\"score_prop\":4.4897959184},{\"name\":\"kuku\",\"ccp\":\"nhamaxaxa\",\"practica\":\"pescadores\",\"score_prop\":2.0408163265},{\"name\":\"mavionho\",\"ccp\":\"nhamaxaxa\",\"practica\":\"pescadores\",\"score_prop\":10.2040816327},{\"name\":\"mifiti\",\"ccp\":\"nhamaxaxa\",\"practica\":\"pescadores\",\"score_prop\":2.8571428571},{\"name\":\"mihili\",\"ccp\":\"nhamaxaxa\",\"practica\":\"pescadores\",\"score_prop\":17.5510204082},{\"name\":\"nhamunhe\",\"ccp\":\"nhamaxaxa\",\"practica\":\"pescadores\",\"score_prop\":1.2244897959},{\"name\":\"nharongue\",\"ccp\":\"nhamaxaxa\",\"practica\":\"pescadores\",\"score_prop\":5.7142857143},{\"name\":\"nhasastani\",\"ccp\":\"nhamaxaxa\",\"practica\":\"pescadores\",\"score_prop\":0.8163265306},{\"name\":\"salani\",\"ccp\":\"nhamaxaxa\",\"practica\":\"pescadores\",\"score_prop\":6.9387755102},{\"name\":\"sardinha\",\"ccp\":\"nhamaxaxa\",\"practica\":\"pescadores\",\"score_prop\":10.2040816327},{\"name\":\"sigulula\",\"ccp\":\"nhamaxaxa\",\"practica\":\"pescadores\",\"score_prop\":11.0204081633},{\"name\":\"simbatsani\",\"ccp\":\"nhamaxaxa\",\"practica\":\"pescadores\",\"score_prop\":0.4081632653},{\"name\":\"tendre\",\"ccp\":\"nhamaxaxa\",\"practica\":\"pescadores\",\"score_prop\":2.8571428571},{\"name\":\"tsakanhani\",\"ccp\":\"nhamaxaxa\",\"practica\":\"pescadores\",\"score_prop\":3.2653061224},{\"name\":\"tsogola\",\"ccp\":\"nhamaxaxa\",\"practica\":\"pescadores\",\"score_prop\":2.8571428571},{\"name\":\"tsongua\",\"ccp\":\"nhamaxaxa\",\"practica\":\"pescadores\",\"score_prop\":4.8979591837},{\"name\":\"xereua\",\"ccp\":\"nhamaxaxa\",\"practica\":\"pescadores\",\"score_prop\":2.4489795918},{\"name\":\"carapo\",\"ccp\":\"nhamua\",\"practica\":\"pescadores\",\"score_prop\":14.2061281337},{\"name\":\"dzindrolo\",\"ccp\":\"nhamua\",\"practica\":\"pescadores\",\"score_prop\":15.5988857939},{\"name\":\"dzipata\",\"ccp\":\"nhamua\",\"practica\":\"pescadores\",\"score_prop\":6.4066852368},{\"name\":\"gidzuani\",\"ccp\":\"nhamua\",\"practica\":\"pescadores\",\"score_prop\":1.6713091922},{\"name\":\"gingave\",\"ccp\":\"nhamua\",\"practica\":\"pescadores\",\"score_prop\":1.6713091922},{\"name\":\"gudua\",\"ccp\":\"nhamua\",\"practica\":\"pescadores\",\"score_prop\":3.8997214485},{\"name\":\"korea\",\"ccp\":\"nhamua\",\"practica\":\"pescadores\",\"score_prop\":7.7994428969},{\"name\":\"mahoma\",\"ccp\":\"nhamua\",\"practica\":\"pescadores\",\"score_prop\":1.3927576602},{\"name\":\"mapalo\",\"ccp\":\"nhamua\",\"practica\":\"pescadores\",\"score_prop\":0.8356545961},{\"name\":\"matewo\",\"ccp\":\"nhamua\",\"practica\":\"pescadores\",\"score_prop\":1.1142061281},{\"name\":\"mavandzi\",\"ccp\":\"nhamua\",\"practica\":\"pescadores\",\"score_prop\":5.0139275766},{\"name\":\"mavionho\",\"ccp\":\"nhamua\",\"practica\":\"pescadores\",\"score_prop\":15.3203342618},{\"name\":\"mihili\",\"ccp\":\"nhamua\",\"practica\":\"pescadores\",\"score_prop\":6.4066852368},{\"name\":\"nhamuele\",\"ccp\":\"nhamua\",\"practica\":\"pescadores\",\"score_prop\":0.8356545961},{\"name\":\"nhamunhe\",\"ccp\":\"nhamua\",\"practica\":\"pescadores\",\"score_prop\":0.8356545961},{\"name\":\"nharongue\",\"ccp\":\"nhamua\",\"practica\":\"pescadores\",\"score_prop\":1.9498607242},{\"name\":\"salani\",\"ccp\":\"nhamua\",\"practica\":\"pescadores\",\"score_prop\":7.5208913649},{\"name\":\"sardinha\",\"ccp\":\"nhamua\",\"practica\":\"pescadores\",\"score_prop\":4.4568245125},{\"name\":\"sigulula\",\"ccp\":\"nhamua\",\"practica\":\"pescadores\",\"score_prop\":0.8356545961},{\"name\":\"tsava\",\"ccp\":\"nhamua\",\"practica\":\"pescadores\",\"score_prop\":0.5571030641},{\"name\":\"tsongua\",\"ccp\":\"nhamua\",\"practica\":\"pescadores\",\"score_prop\":1.6713091922},{\"name\":\"carapo\",\"ccp\":\"njuga\",\"practica\":\"pescadores\",\"score_prop\":5.223880597},{\"name\":\"dzindrolo\",\"ccp\":\"njuga\",\"practica\":\"pescadores\",\"score_prop\":5.223880597},{\"name\":\"dzipata\",\"ccp\":\"njuga\",\"practica\":\"pescadores\",\"score_prop\":14.552238806},{\"name\":\"guikhokoroma\",\"ccp\":\"njuga\",\"practica\":\"pescadores\",\"score_prop\":2.6119402985},{\"name\":\"likerere\",\"ccp\":\"njuga\",\"practica\":\"pescadores\",\"score_prop\":1.8656716418},{\"name\":\"mavionho\",\"ccp\":\"njuga\",\"practica\":\"pescadores\",\"score_prop\":11.9402985075},{\"name\":\"mihili\",\"ccp\":\"njuga\",\"practica\":\"pescadores\",\"score_prop\":23.1343283582},{\"name\":\"nhabugue\",\"ccp\":\"njuga\",\"practica\":\"pescadores\",\"score_prop\":3.3582089552},{\"name\":\"nharongue\",\"ccp\":\"njuga\",\"practica\":\"pescadores\",\"score_prop\":2.9850746269},{\"name\":\"salani\",\"ccp\":\"njuga\",\"practica\":\"pescadores\",\"score_prop\":2.6119402985},{\"name\":\"sigulula\",\"ccp\":\"njuga\",\"practica\":\"pescadores\",\"score_prop\":18.2835820896},{\"name\":\"tsava\",\"ccp\":\"njuga\",\"practica\":\"pescadores\",\"score_prop\":4.8507462687},{\"name\":\"tsongua\",\"ccp\":\"njuga\",\"practica\":\"pescadores\",\"score_prop\":3.3582089552},{\"name\":\"dzindrolo\",\"ccp\":\"chamane\",\"practica\":\"pescadores\",\"score_prop\":7.0993914807},{\"name\":\"dzipata\",\"ccp\":\"chamane\",\"practica\":\"pescadores\",\"score_prop\":7.200811359},{\"name\":\"gihologo\",\"ccp\":\"chamane\",\"practica\":\"pescadores\",\"score_prop\":1.4198782961},{\"name\":\"gingave\",\"ccp\":\"chamane\",\"practica\":\"pescadores\",\"score_prop\":0.7099391481},{\"name\":\"gitongwe\",\"ccp\":\"chamane\",\"practica\":\"pescadores\",\"score_prop\":0.9127789047},{\"name\":\"gudua\",\"ccp\":\"chamane\",\"practica\":\"pescadores\",\"score_prop\":1.5212981744},{\"name\":\"guikhokoroma\",\"ccp\":\"chamane\",\"practica\":\"pescadores\",\"score_prop\":0.2028397566},{\"name\":\"honho\",\"ccp\":\"chamane\",\"practica\":\"pescadores\",\"score_prop\":1.8255578093},{\"name\":\"kuku\",\"ccp\":\"chamane\",\"practica\":\"pescadores\",\"score_prop\":0.9127789047},{\"name\":\"makolo\",\"ccp\":\"chamane\",\"practica\":\"pescadores\",\"score_prop\":0.3042596349},{\"name\":\"mapalo\",\"ccp\":\"chamane\",\"practica\":\"pescadores\",\"score_prop\":1.2170385396},{\"name\":\"masaba\",\"ccp\":\"chamane\",\"practica\":\"pescadores\",\"score_prop\":1.4198782961},{\"name\":\"matewo\",\"ccp\":\"chamane\",\"practica\":\"pescadores\",\"score_prop\":0.4056795132},{\"name\":\"mavandzi\",\"ccp\":\"chamane\",\"practica\":\"pescadores\",\"score_prop\":5.476673428},{\"name\":\"mavionho\",\"ccp\":\"chamane\",\"practica\":\"pescadores\",\"score_prop\":15.415821501},{\"name\":\"mbabe\",\"ccp\":\"chamane\",\"practica\":\"pescadores\",\"score_prop\":0.6085192698},{\"name\":\"mifiti\",\"ccp\":\"chamane\",\"practica\":\"pescadores\",\"score_prop\":0.4056795132},{\"name\":\"mihili\",\"ccp\":\"chamane\",\"practica\":\"pescadores\",\"score_prop\":12.2718052738},{\"name\":\"mwahaha\",\"ccp\":\"chamane\",\"practica\":\"pescadores\",\"score_prop\":0.8113590264},{\"name\":\"nhamuele\",\"ccp\":\"chamane\",\"practica\":\"pescadores\",\"score_prop\":0.3042596349},{\"name\":\"nharongue\",\"ccp\":\"chamane\",\"practica\":\"pescadores\",\"score_prop\":4.7667342799},{\"name\":\"nhasastani\",\"ccp\":\"chamane\",\"practica\":\"pescadores\",\"score_prop\":0.1014198783},{\"name\":\"nvuma\",\"ccp\":\"chamane\",\"practica\":\"pescadores\",\"score_prop\":0.2028397566},{\"name\":\"salani\",\"ccp\":\"chamane\",\"practica\":\"pescadores\",\"score_prop\":17.7484787018},{\"name\":\"sardinha\",\"ccp\":\"chamane\",\"practica\":\"pescadores\",\"score_prop\":1.2170385396},{\"name\":\"sigulula\",\"ccp\":\"chamane\",\"practica\":\"pescadores\",\"score_prop\":5.476673428},{\"name\":\"tendre\",\"ccp\":\"chamane\",\"practica\":\"pescadores\",\"score_prop\":1.8255578093},{\"name\":\"togoma\",\"ccp\":\"chamane\",\"practica\":\"pescadores\",\"score_prop\":0.6085192698},{\"name\":\"tsanga\",\"ccp\":\"chamane\",\"practica\":\"pescadores\",\"score_prop\":0.7099391481},{\"name\":\"tsogola\",\"ccp\":\"chamane\",\"practica\":\"pescadores\",\"score_prop\":1.6227180527},{\"name\":\"tsongua\",\"ccp\":\"chamane\",\"practica\":\"pescadores\",\"score_prop\":0.3042596349},{\"name\":\"xereua\",\"ccp\":\"chamane\",\"practica\":\"pescadores\",\"score_prop\":4.9695740365},{\"name\":\"dzindrolo\",\"ccp\":\"marrambone\",\"practica\":\"pescadores\",\"score_prop\":7.9872204473},{\"name\":\"dzipata\",\"ccp\":\"marrambone\",\"practica\":\"pescadores\",\"score_prop\":1.2779552716},{\"name\":\"gitongwe\",\"ccp\":\"marrambone\",\"practica\":\"pescadores\",\"score_prop\":5.750798722},{\"name\":\"gudua\",\"ccp\":\"marrambone\",\"practica\":\"pescadores\",\"score_prop\":0.9584664537},{\"name\":\"honho\",\"ccp\":\"marrambone\",\"practica\":\"pescadores\",\"score_prop\":0.6389776358},{\"name\":\"mavandzi\",\"ccp\":\"marrambone\",\"practica\":\"pescadores\",\"score_prop\":7.0287539936},{\"name\":\"mavionho\",\"ccp\":\"marrambone\",\"practica\":\"pescadores\",\"score_prop\":11.1821086262},{\"name\":\"mbabe\",\"ccp\":\"marrambone\",\"practica\":\"pescadores\",\"score_prop\":8.3067092652},{\"name\":\"mihili\",\"ccp\":\"marrambone\",\"practica\":\"pescadores\",\"score_prop\":14.3769968051},{\"name\":\"ngi\",\"ccp\":\"marrambone\",\"practica\":\"pescadores\",\"score_prop\":3.1948881789},{\"name\":\"nhabugue\",\"ccp\":\"marrambone\",\"practica\":\"pescadores\",\"score_prop\":9.2651757188},{\"name\":\"nharongue\",\"ccp\":\"marrambone\",\"practica\":\"pescadores\",\"score_prop\":1.2779552716},{\"name\":\"salani\",\"ccp\":\"marrambone\",\"practica\":\"pescadores\",\"score_prop\":7.3482428115},{\"name\":\"sigulula\",\"ccp\":\"marrambone\",\"practica\":\"pescadores\",\"score_prop\":10.2236421725},{\"name\":\"sololo\",\"ccp\":\"marrambone\",\"practica\":\"pescadores\",\"score_prop\":1.5974440895},{\"name\":\"tsongua\",\"ccp\":\"marrambone\",\"practica\":\"pescadores\",\"score_prop\":9.5846645367},{\"name\":\"dzindrolo\",\"ccp\":\"nhampossa\",\"practica\":\"pescadores\",\"score_prop\":8.9005235602},{\"name\":\"dzipata\",\"ccp\":\"nhampossa\",\"practica\":\"pescadores\",\"score_prop\":6.2827225131},{\"name\":\"gihologo\",\"ccp\":\"nhampossa\",\"practica\":\"pescadores\",\"score_prop\":3.664921466},{\"name\":\"gitongwe\",\"ccp\":\"nhampossa\",\"practica\":\"pescadores\",\"score_prop\":4.7120418848},{\"name\":\"gudua\",\"ccp\":\"nhampossa\",\"practica\":\"pescadores\",\"score_prop\":4.7120418848},{\"name\":\"honho\",\"ccp\":\"nhampossa\",\"practica\":\"pescadores\",\"score_prop\":3.664921466},{\"name\":\"masaba\",\"ccp\":\"nhampossa\",\"practica\":\"pescadores\",\"score_prop\":1.5706806283},{\"name\":\"mavandzi\",\"ccp\":\"nhampossa\",\"practica\":\"pescadores\",\"score_prop\":4.7120418848},{\"name\":\"mavionho\",\"ccp\":\"nhampossa\",\"practica\":\"pescadores\",\"score_prop\":3.664921466},{\"name\":\"mbabe\",\"ccp\":\"nhampossa\",\"practica\":\"pescadores\",\"score_prop\":7.3298429319},{\"name\":\"mihili\",\"ccp\":\"nhampossa\",\"practica\":\"pescadores\",\"score_prop\":6.8062827225},{\"name\":\"nhabugue\",\"ccp\":\"nhampossa\",\"practica\":\"pescadores\",\"score_prop\":4.1884816754},{\"name\":\"nharongue\",\"ccp\":\"nhampossa\",\"practica\":\"pescadores\",\"score_prop\":13.612565445},{\"name\":\"salani\",\"ccp\":\"nhampossa\",\"practica\":\"pescadores\",\"score_prop\":3.1413612565},{\"name\":\"sigulula\",\"ccp\":\"nhampossa\",\"practica\":\"pescadores\",\"score_prop\":9.9476439791},{\"name\":\"tendre\",\"ccp\":\"nhampossa\",\"practica\":\"pescadores\",\"score_prop\":3.1413612565},{\"name\":\"tsongua\",\"ccp\":\"nhampossa\",\"practica\":\"pescadores\",\"score_prop\":3.664921466},{\"name\":\"xereua\",\"ccp\":\"nhampossa\",\"practica\":\"pescadores\",\"score_prop\":6.2827225131},{\"name\":\"dzindrolo\",\"ccp\":\"sahane\",\"practica\":\"pescadores\",\"score_prop\":4.347826087},{\"name\":\"dzipata\",\"ccp\":\"sahane\",\"practica\":\"pescadores\",\"score_prop\":8.0745341615},{\"name\":\"gihologo\",\"ccp\":\"sahane\",\"practica\":\"pescadores\",\"score_prop\":5.5900621118},{\"name\":\"gitongwe\",\"ccp\":\"sahane\",\"practica\":\"pescadores\",\"score_prop\":4.347826087},{\"name\":\"gudua\",\"ccp\":\"sahane\",\"practica\":\"pescadores\",\"score_prop\":2.4844720497},{\"name\":\"honho\",\"ccp\":\"sahane\",\"practica\":\"pescadores\",\"score_prop\":3.1055900621},{\"name\":\"kolokolo\",\"ccp\":\"sahane\",\"practica\":\"pescadores\",\"score_prop\":5.5900621118},{\"name\":\"masaba\",\"ccp\":\"sahane\",\"practica\":\"pescadores\",\"score_prop\":1.8633540373},{\"name\":\"mavionho\",\"ccp\":\"sahane\",\"practica\":\"pescadores\",\"score_prop\":3.7267080745},{\"name\":\"mbabe\",\"ccp\":\"sahane\",\"practica\":\"pescadores\",\"score_prop\":4.347826087},{\"name\":\"mihili\",\"ccp\":\"sahane\",\"practica\":\"pescadores\",\"score_prop\":16.7701863354},{\"name\":\"nhabugue\",\"ccp\":\"sahane\",\"practica\":\"pescadores\",\"score_prop\":5.5900621118},{\"name\":\"nharongue\",\"ccp\":\"sahane\",\"practica\":\"pescadores\",\"score_prop\":4.9689440994},{\"name\":\"sigulula\",\"ccp\":\"sahane\",\"practica\":\"pescadores\",\"score_prop\":8.6956521739},{\"name\":\"sololo\",\"ccp\":\"sahane\",\"practica\":\"pescadores\",\"score_prop\":2.4844720497},{\"name\":\"tendre\",\"ccp\":\"sahane\",\"practica\":\"pescadores\",\"score_prop\":4.9689440994},{\"name\":\"tsongua\",\"ccp\":\"sahane\",\"practica\":\"pescadores\",\"score_prop\":9.3167701863},{\"name\":\"xereua\",\"ccp\":\"sahane\",\"practica\":\"pescadores\",\"score_prop\":3.7267080745},{\"name\":\"dzipata\",\"ccp\":\"muele\",\"practica\":\"pescadores\",\"score_prop\":7.1428571429},{\"name\":\"mavionho\",\"ccp\":\"muele\",\"practica\":\"pescadores\",\"score_prop\":11.9047619048},{\"name\":\"mbabe\",\"ccp\":\"muele\",\"practica\":\"pescadores\",\"score_prop\":9.5238095238},{\"name\":\"mihili\",\"ccp\":\"muele\",\"practica\":\"pescadores\",\"score_prop\":16.6666666667},{\"name\":\"salani\",\"ccp\":\"muele\",\"practica\":\"pescadores\",\"score_prop\":21.4285714286},{\"name\":\"tsongua\",\"ccp\":\"muele\",\"practica\":\"pescadores\",\"score_prop\":14.2857142857},{\"name\":\"xereua\",\"ccp\":\"muele\",\"practica\":\"pescadores\",\"score_prop\":19.0476190476},{\"name\":\"49\",\"ccp\":\"baia\",\"practica\":\"pescadores\",\"score_prop\":0.0753012048},{\"name\":\"carapo\",\"ccp\":\"baia\",\"practica\":\"pescadores\",\"score_prop\":3.5517068273},{\"name\":\"dzindrolo\",\"ccp\":\"baia\",\"practica\":\"pescadores\",\"score_prop\":6.6641566265},{\"name\":\"dzipata\",\"ccp\":\"baia\",\"practica\":\"pescadores\",\"score_prop\":5.4718875502},{\"name\":\"gidagianha\",\"ccp\":\"baia\",\"practica\":\"pescadores\",\"score_prop\":0.0753012048},{\"name\":\"gidzuani\",\"ccp\":\"baia\",\"practica\":\"pescadores\",\"score_prop\":0.1129518072},{\"name\":\"gihologo\",\"ccp\":\"baia\",\"practica\":\"pescadores\",\"score_prop\":4.2168674699},{\"name\":\"gingave\",\"ccp\":\"baia\",\"practica\":\"pescadores\",\"score_prop\":0.1757028112},{\"name\":\"gitongwe\",\"ccp\":\"baia\",\"practica\":\"pescadores\",\"score_prop\":1.8323293173},{\"name\":\"gudua\",\"ccp\":\"baia\",\"practica\":\"pescadores\",\"score_prop\":3.0873493976},{\"name\":\"guikhokoroma\",\"ccp\":\"baia\",\"practica\":\"pescadores\",\"score_prop\":0.1129518072},{\"name\":\"honho\",\"ccp\":\"baia\",\"practica\":\"pescadores\",\"score_prop\":3.0873493976},{\"name\":\"kolokolo\",\"ccp\":\"baia\",\"practica\":\"pescadores\",\"score_prop\":0.5145582329},{\"name\":\"korea\",\"ccp\":\"baia\",\"practica\":\"pescadores\",\"score_prop\":0.6149598394},{\"name\":\"kuku\",\"ccp\":\"baia\",\"practica\":\"pescadores\",\"score_prop\":0.5396586345},{\"name\":\"lidume\",\"ccp\":\"baia\",\"practica\":\"pescadores\",\"score_prop\":0.3514056225},{\"name\":\"likerere\",\"ccp\":\"baia\",\"practica\":\"pescadores\",\"score_prop\":0.2761044177},{\"name\":\"livandrevandre\",\"ccp\":\"baia\",\"practica\":\"pescadores\",\"score_prop\":0.0251004016},{\"name\":\"magumba\",\"ccp\":\"baia\",\"practica\":\"pescadores\",\"score_prop\":1.0542168675},{\"name\":\"mahoma\",\"ccp\":\"baia\",\"practica\":\"pescadores\",\"score_prop\":0.0753012048},{\"name\":\"makolo\",\"ccp\":\"baia\",\"practica\":\"pescadores\",\"score_prop\":0.1631526104},{\"name\":\"mapalo\",\"ccp\":\"baia\",\"practica\":\"pescadores\",\"score_prop\":0.3012048193},{\"name\":\"marengue\",\"ccp\":\"baia\",\"practica\":\"pescadores\",\"score_prop\":0.0125502008},{\"name\":\"masaba\",\"ccp\":\"baia\",\"practica\":\"pescadores\",\"score_prop\":6.187248996},{\"name\":\"matewo\",\"ccp\":\"baia\",\"practica\":\"pescadores\",\"score_prop\":0.2886546185},{\"name\":\"mavandzi\",\"ccp\":\"baia\",\"practica\":\"pescadores\",\"score_prop\":13.3534136546},{\"name\":\"mavionho\",\"ccp\":\"baia\",\"practica\":\"pescadores\",\"score_prop\":7.1285140562},{\"name\":\"mbabe\",\"ccp\":\"baia\",\"practica\":\"pescadores\",\"score_prop\":1.9452811245},{\"name\":\"mifiti\",\"ccp\":\"baia\",\"practica\":\"pescadores\",\"score_prop\":1.2173694779},{\"name\":\"mihili\",\"ccp\":\"baia\",\"practica\":\"pescadores\",\"score_prop\":9.6385542169},{\"name\":\"mitifa\",\"ccp\":\"baia\",\"practica\":\"pescadores\",\"score_prop\":0.3263052209},{\"name\":\"mwahaha\",\"ccp\":\"baia\",\"practica\":\"pescadores\",\"score_prop\":0.1004016064},{\"name\":\"nani\",\"ccp\":\"baia\",\"practica\":\"pescadores\",\"score_prop\":0.1757028112},{\"name\":\"ngee\",\"ccp\":\"baia\",\"practica\":\"pescadores\",\"score_prop\":0.1129518072},{\"name\":\"ngi\",\"ccp\":\"baia\",\"practica\":\"pescadores\",\"score_prop\":0.125502008},{\"name\":\"nhabugue\",\"ccp\":\"baia\",\"practica\":\"pescadores\",\"score_prop\":1.2675702811},{\"name\":\"nhakomani\",\"ccp\":\"baia\",\"practica\":\"pescadores\",\"score_prop\":1.0918674699},{\"name\":\"nhamuele\",\"ccp\":\"baia\",\"practica\":\"pescadores\",\"score_prop\":0.0753012048},{\"name\":\"nhamunhe\",\"ccp\":\"baia\",\"practica\":\"pescadores\",\"score_prop\":0.0753012048},{\"name\":\"nhanguedwa\",\"ccp\":\"baia\",\"practica\":\"pescadores\",\"score_prop\":0.062751004},{\"name\":\"nharongue\",\"ccp\":\"baia\",\"practica\":\"pescadores\",\"score_prop\":2.9116465863},{\"name\":\"nhasastani\",\"ccp\":\"baia\",\"practica\":\"pescadores\",\"score_prop\":0.0376506024},{\"name\":\"nhatogue\",\"ccp\":\"baia\",\"practica\":\"pescadores\",\"score_prop\":0.0376506024},{\"name\":\"nvuma\",\"ccp\":\"baia\",\"practica\":\"pescadores\",\"score_prop\":0.0251004016},{\"name\":\"salani\",\"ccp\":\"baia\",\"practica\":\"pescadores\",\"score_prop\":6.2374497992},{\"name\":\"sardinha\",\"ccp\":\"baia\",\"practica\":\"pescadores\",\"score_prop\":0.8785140562},{\"name\":\"sigulula\",\"ccp\":\"baia\",\"practica\":\"pescadores\",\"score_prop\":4.4051204819},{\"name\":\"sikwalala\",\"ccp\":\"baia\",\"practica\":\"pescadores\",\"score_prop\":0.0502008032},{\"name\":\"simbatsani\",\"ccp\":\"baia\",\"practica\":\"pescadores\",\"score_prop\":0.0125502008},{\"name\":\"sololo\",\"ccp\":\"baia\",\"practica\":\"pescadores\",\"score_prop\":0.3639558233},{\"name\":\"tendre\",\"ccp\":\"baia\",\"practica\":\"pescadores\",\"score_prop\":1.7319277108},{\"name\":\"togoma\",\"ccp\":\"baia\",\"practica\":\"pescadores\",\"score_prop\":0.1757028112},{\"name\":\"tsakanhani\",\"ccp\":\"baia\",\"practica\":\"pescadores\",\"score_prop\":0.7279116466},{\"name\":\"tsanga\",\"ccp\":\"baia\",\"practica\":\"pescadores\",\"score_prop\":0.0878514056},{\"name\":\"tsava\",\"ccp\":\"baia\",\"practica\":\"pescadores\",\"score_prop\":2.3970883534},{\"name\":\"tsogola\",\"ccp\":\"baia\",\"practica\":\"pescadores\",\"score_prop\":0.3639558233},{\"name\":\"tsongua\",\"ccp\":\"baia\",\"practica\":\"pescadores\",\"score_prop\":1.8825301205},{\"name\":\"xereua\",\"ccp\":\"baia\",\"practica\":\"pescadores\",\"score_prop\":2.1084337349}]"}], "signals": [{"name": "tooltip", "value": {}, "on": [{"events": "rect:mouseover", "update": "datum"}, {"events": "rect:mouseout", "update": "{}"}]}, {"name": "Practica", "value": "apanhadores", "bind": {"input": "select", "options": ["apanhadores", "pescadores"]}}, {"name": "CCP", "value": "baia", "bind": {"input": "select", "options": ["baia", "ilha", "nhamua", "josina_machel", "chamane", "marrambone", "mucucune", "nhampossa", "madava", "kuguana", "nhamaxaxa", "sahane", "njuga", "morrumbene"]}}], "scales": [{"name": "yscale", "type": "band", "domain": {"data": "table", "field": "name", "sort": {"op": "median", "field": "score_prop", "order": "descending"}}, "range": "height", "padding": 0.02}, {"name": "xscale", "type": "linear", "domain": {"data": "table", "field": "score_prop"}, "round": true, "zero": true, "nice": true, "range": "width"}, {"name": "opacity", "type": "ordinal", "domain": {"data": "table", "field": "name", "sort": {"op": "median", "field": "score_prop", "order": "descending"}}, "range": [1, 1, 1, 0.5, 0.5, 0.5, 0.5, 0.5, 0.5, 0.5, 0.5, 0.5, 0.5, 0.5, 0.5, 0.5, 0.5, 0.5, 0.5, 0.5, 0.5, 0.5, 0.5, 0.5, 0.5, 0.5, 0.5, 0.5, 0.5, 0.5, 0.5]}], "axes": [{"orient": "bottom", "scale": "xscale", "title": "Score"}, {"orient": "left", "scale": "yscale", "tickSize": 0, "labelPadding": 4, "zindex": 1}], "title": {"text": {"signal": "CCP=='baia' ? 'Recursos importantes para ' +Practica + ' a longo da Baia de Inhambane': 'Recursos importantes para os ' + Practica + ' de ' + CCP"}, "orient": "top"}, "marks": [{"type": "rect", "from": {"data": "table"}, "encode": {"enter": {"y": {"scale": "yscale", "field": "name"}, "x": {"scale": "xscale", "field": "score_prop"}, "x2": {"scale": "xscale", "value": 0}, "height": {"scale": "yscale", "band": 1}}, "update": {"fill": {"value": "#8da0cb"}, "opacity": {"scale": "opacity", "field": "name"}}, "hover": {"fill": {"value": "#fc8d62"}}}}, {"type": "text", "encode": {"enter": {"align": {"value": "center"}, "baseline": {"value": "bottom"}, "fill": {"value": "grey"}}, "update": {"x": {"scale": "xscale", "signal": "tooltip.score_prop", "offset": 15, "band": 1}, "y": {"scale": "yscale", "signal": "tooltip.name", "offset": 15}, "text": {"signal": "tooltip.score_prop"}, "fillOpacity": [{"test": "datum === tooltip", "value": 0}, {"value": 1}]}}}]}